rdfobject
