Metadata-Version: 1.0
Name: RDFobject
Version: 0.4.2
Summary: RDFobject - classes for dealing with entities and things in RDF
Home-page: UNKNOWN
Author: Ben O'Steen
Author-email: bosteen@gmail.com
License: UNKNOWN
Platform: UNKNOWN
